dictdiffer/__init__.py
dictdiffer/_compat.py
dictdiffer/conflict.py
dictdiffer/merge.py
dictdiffer/resolve.py
dictdiffer/unify.py
dictdiffer/utils.py
dictdiffer/version.py
dictdiffer_jira_offline_fork-0.0.1.dist-info/AUTHORS
dictdiffer_jira_offline_fork-0.0.1.dist-info/LICENSE
dictdiffer_jira_offline_fork-0.0.1.dist-info/METADATA
dictdiffer_jira_offline_fork-0.0.1.dist-info/WHEEL
dictdiffer_jira_offline_fork-0.0.1.dist-info/top_level.txt
dictdiffer_jira_offline_fork-0.0.1.dist-info/RECORD
